Metadata-Version: 2.1
Name: modeldocumentation
Version: 0.0.3
Summary: A model documneter for power bi files
Home-page: 
Author: Ayush Jain
Author-email: jainaayush051@outlook.com
License: MIT
Classifier: Development Status :: 5 - Production/Stable
Classifier: Intended Audience :: Education
Classifier: Operating System :: Microsoft :: Windows :: Windows 11
Classifier: License :: OSI Approved :: MIT License
Classifier: Programming Language :: Python :: 3
License-File: LICENSE.txt
